<?xml version="1.0" encoding="utf-8"?>
<Database>
	<Kinds>
		<InsertOrIgnore Kind="KIND_CONSTRUCTIBLE"/>
	</Kinds>
	<Types>
		<Row Type="DISTRICT_UNIQUE_SCHOLAREUM" Kind="KIND_QUARTER"/>
	</Types>
	<UniqueQuarters>
		<Row UniqueQuarterType="DISTRICT_UNIQUE_SCHOLAREUM" BuildingType1="BUILDING_LIBRARY" BuildingType2="BUILDING_GARDEN" Name="LOC_DISTRICT_UNIQUE_SCHOLAR_GARDEN_NAME" Description="LOC_DISTRICT_UNIQUE_SCHOLAR_GARDEN_DESCRIPTION"/>
	</UniqueQuarters>
	<UniqueQuarterModifiers>
		<Row UniqueQuarterType="DISTRICT_UNIQUE_SCHOLAREUM" ModifierId="MOD_SCHOLAREUM_EFFECT"/>
	</UniqueQuarterModifiers>
</Database>